lanisapi/__init__.py
lanisapi/client.py
lanisapi/constants.py
lanisapi/exceptions.py
lanisapi/functions/__init__.py
lanisapi/functions/apps.py
lanisapi/functions/authentication_types.py
lanisapi/functions/calendar.py
lanisapi/functions/conversations.py
lanisapi/functions/schools.py
lanisapi/functions/substitution.py
lanisapi/functions/tasks.py
lanisapi/helpers/__init__.py
lanisapi/helpers/authentication.py
lanisapi/helpers/cryptor.py
lanisapi/helpers/html_logger.py
lanisapi/helpers/request.py
lanisapi/helpers/wrappers.py
lanisapi-0.4.1.dist-info/LICENSE
lanisapi-0.4.1.dist-info/METADATA
lanisapi-0.4.1.dist-info/WHEEL
lanisapi-0.4.1.dist-info/top_level.txt
lanisapi-0.4.1.dist-info/RECORD
