Metadata-Version: 2.1
Name: lanisapi
Version: 0.4.1
Summary: A unofficial python api for Lanis.
Author: kurwjan
Project-URL: Homepage, https://github.com/kurwjan/LanisAPI
Project-URL: Bug Tracker, https://github.com/kurwjan/LanisAPI/issues
Project-URL: Documentation, https://lanisapi.readthedocs.io/
Keywords: Lanis,SPH,Schulportal Hessen,Hessen,API
Classifier: Programming Language :: Python :: 3
Classifier: License :: OSI Approved :: MIT License
Classifier: Operating System :: OS Independent
Classifier: Natural Language :: German
Requires-Python: >=3.7
License-File: LICENSE
Requires-Dist: httpx
Requires-Dist: selectolax
Requires-Dist: pycryptodomex
Requires-Dist: py-machineid
